edc_utils/__init__.py
edc_utils/age.py
edc_utils/apps.py
edc_utils/celery.py
edc_utils/context_processors_check.py
edc_utils/dashboard_middleware_check.py
edc_utils/date.py
edc_utils/disable_signals.py
edc_utils/get_datetime_from_env.py
edc_utils/get_static_file.py
edc_utils/get_uuid.py
edc_utils/message_in_queue.py
edc_utils/paths_for_urlpatterns.py
edc_utils/round_up.py
edc_utils/show_urls.py
edc_utils/sqlite.py
edc_utils/text.py
edc_utils/logging_filters/__init__.py
edc_utils/logging_filters/ignore_specific_ip_disallowed_host.py
edc_utils/test_case_mixins/__init__.py
edc_utils/test_case_mixins/longitudinal_test_case_mixin.py
edc_utils/test_case_mixins/visit_tracking_test_case_mixins.py
edc_utils/tests/__init__.py
edc_utils/tests/test_settings.py
edc_utils/tests/test_utils.py
edc_utils/tests/urls.py
edc_utils/tests/etc/user-aes-local.key
edc_utils/tests/etc/user-aes-restricted.key
edc_utils/tests/etc/user-rsa-local-private.pem
edc_utils/tests/etc/user-rsa-local-public.pem
edc_utils/tests/etc/user-rsa-restricted-private.pem
edc_utils/tests/etc/user-rsa-restricted-public.pem
edc_utils/tests/etc/user-salt-local.key
edc_utils/tests/etc/user-salt-restricted.key
edc_utils-1.1.1.dist-info/licenses/AUTHORS.rst
edc_utils-1.1.1.dist-info/licenses/LICENSE
edc_utils-1.1.1.dist-info/METADATA
edc_utils-1.1.1.dist-info/WHEEL
edc_utils-1.1.1.dist-info/top_level.txt
edc_utils-1.1.1.dist-info/RECORD
